README.md
setup.py
lcircle/__init__.py
lcircle/lcircle.py
lcircle.egg-info/PKG-INFO
lcircle.egg-info/SOURCES.txt
lcircle.egg-info/dependency_links.txt
lcircle.egg-info/entry_points.txt
lcircle.egg-info/requires.txt
lcircle.egg-info/top_level.txt