Metadata-Version: 1.2
Name: lcircle
Version: 0.0.1.post1556111555
Summary: local test runner for circleci
Home-page: https://github.com/chestm007/lcircle
Author: Max Chesterfield
Author-email: chestm007@hotmail.com
Maintainer: Max Chesterfield
Maintainer-email: chestm007@hotmail.com
License: GPL-2.0
Platform: UNKNOWN
